TypeEnforcement/__init__.py
TypeEnforcement/exceptions.py
TypeEnforcement/type_enforcer.py
TypeEnforcer-1.5.0.dist-info/LICENSE
TypeEnforcer-1.5.0.dist-info/METADATA
TypeEnforcer-1.5.0.dist-info/WHEEL
TypeEnforcer-1.5.0.dist-info/top_level.txt
TypeEnforcer-1.5.0.dist-info/RECORD
