Metadata-Version: 2.1
Name: TypeEnforcer
Version: 1.5.0
Summary: enforce python type hints
Author-email: Michael Ray <m.ray37990@gmail.com>
License: Copyright 2023 Michael Ray
Project-URL: Homepage, https://github.com/MalinkyZubr/TypeEnforcer.git
Keywords: types,typing,static typing
Classifier: License :: OSI Approved :: MIT License
Classifier: Programming Language :: Python
Classifier: Programming Language :: Python :: 3
Requires-Python: >=3.9
License-File: LICENSE
Provides-Extra: dev
